lifesimmc/__init__.py
lifesimmc/__main__.py
lifesimmc/core/__init__.py
lifesimmc/core/modules/__init__.py
lifesimmc/core/modules/_old/__init__.py
lifesimmc/core/modules/_old/analytical_mle_module.py
lifesimmc/core/modules/_old/covariance_calculation_module2.py
lifesimmc/core/modules/_old/false_color_image_module.py
lifesimmc/core/modules/_old/lay2006.py
lifesimmc/core/modules/_old/ls_extraction_module.py
lifesimmc/core/modules/_old/mcmc_extraction_module2.py
lifesimmc/core/modules/_old/mcmc_extraction_module_0.py
lifesimmc/core/modules/_old/mcmc_module.py
lifesimmc/core/modules/_old/ml_detection_2.py
lifesimmc/core/modules/_old/ml_detection_2_bb.py
lifesimmc/core/modules/_old/ml_detection_3.py
lifesimmc/core/modules/_old/ml_detection_module.py
lifesimmc/core/modules/_old/polynomial_subtraction_module.py
lifesimmc/core/modules/_old/polynomial_subtraction_module2.py
lifesimmc/core/modules/_old/rgb_image_module.py
lifesimmc/core/modules/_old/spectrum_fitting_module.py
lifesimmc/core/modules/_old/template_loading_module.py
lifesimmc/core/modules/base_module.py
lifesimmc/core/modules/generating/__init__.py
lifesimmc/core/modules/generating/data_generation_module.py
lifesimmc/core/modules/generating/template_generation_module.py
lifesimmc/core/modules/loading/__init__.py
lifesimmc/core/modules/loading/setup_module.py
lifesimmc/core/modules/processing/__init__.py
lifesimmc/core/modules/processing/_old/__init__.py
lifesimmc/core/modules/processing/_old/lay2006.py
lifesimmc/core/modules/processing/_old/ls_extraction_module.py
lifesimmc/core/modules/processing/_old/mcmc_extraction_module2.py
lifesimmc/core/modules/processing/_old/mcmc_extraction_module_0.py
lifesimmc/core/modules/processing/_old/ml_detection_2.py
lifesimmc/core/modules/processing/_old/ml_detection_2_bb.py
lifesimmc/core/modules/processing/_old/ml_detection_3.py
lifesimmc/core/modules/processing/_old/ml_detection_module.py
lifesimmc/core/modules/processing/_old/ml_detection_module_cov.py
lifesimmc-1.1.2.dist-info/METADATA
lifesimmc-1.1.2.dist-info/WHEEL
lifesimmc-1.1.2.dist-info/entry_points.txt
lifesimmc-1.1.2.dist-info/licenses/LICENSE
lifesimmc-1.1.2.dist-info/RECORD
