Metadata-Version: 2.4
Name: lifesimmc
Version: 1.1.2
Summary: LIFEsimMC
License: GPL-3.0
License-File: LICENSE
Author: Philipp A. Huber
Author-email: huberph@phys.ehtz.ch
Requires-Python: >=3.10
Classifier: Development Status :: 3 - Alpha
Classifier: License :: OSI Approved :: GNU General Public License v3 (GPLv3)
Classifier: Programming Language :: Python :: 3
Classifier: Programming Language :: Python :: 3.10
Classifier: Programming Language :: Python :: 3.11
Classifier: Programming Language :: Python :: 3.12
Classifier: Programming Language :: Python :: 3.13
Classifier: Programming Language :: Python :: 3.14
Requires-Dist: click (>=8.0.1)
Requires-Dist: lmfit (>=1.3.3,<2.0.0)
Requires-Dist: packaging (==23.2)
Requires-Dist: phringe (>=1.0.0,<2.0.0)
Requires-Dist: sphinx-copybutton (>=0.5.2,<0.6.0)
Project-URL: Changelog, https://github.com/pahuber/lifesimmc/releases
Project-URL: Documentation, https://lifesimmc.readthedocs.io
Project-URL: Homepage, https://github.com/pahuber/lifesimmc
Project-URL: Repository, https://github.com/pahuber/lifesimmc
